DBAnomTransformer/__init__.py
DBAnomTransformer/detector.py
DBAnomTransformer/main.py
DBAnomTransformer/solver.py
DBAnomTransformer/config/__init__.py
DBAnomTransformer/config/default.yaml
DBAnomTransformer/config/utils.py
DBAnomTransformer/data_factory/__init__.py
DBAnomTransformer/data_factory/convert_dbsherlock.py
DBAnomTransformer/data_factory/data.py
DBAnomTransformer/data_factory/dataloader.py
DBAnomTransformer/data_factory/process.py
DBAnomTransformer/data_factory/utils.py
DBAnomTransformer/data_factory/dataset/__init__.py
DBAnomTransformer/data_factory/dataset/base.py
DBAnomTransformer/data_factory/dataset/dbsherlock.py
DBAnomTransformer/data_factory/dataset/eda.py
DBAnomTransformer/data_factory/dataset/msl.py
DBAnomTransformer/data_factory/dataset/psm.py
DBAnomTransformer/data_factory/dataset/smap.py
DBAnomTransformer/data_factory/dataset/smd.py
DBAnomTransformer/model/AnomalyTransformer.py
DBAnomTransformer/model/__init__.py
DBAnomTransformer/model/attn.py
DBAnomTransformer/model/embed.py
DBAnomTransformer/utils/__init__.py
DBAnomTransformer/utils/logger.py
DBAnomTransformer/utils/utils.py
dbanomtransformer-0.1.14.dist-info/METADATA
dbanomtransformer-0.1.14.dist-info/WHEEL
dbanomtransformer-0.1.14.dist-info/licenses/LICENSE
dbanomtransformer-0.1.14.dist-info/RECORD
