Metadata-Version: 2.1
Name: DBAnomTransformer
Version: 0.1.14
Summary: A collection of useful util functions
Project-URL: Homepage, https://github.com/pshlego/Anomaly_Explanation
Project-URL: Bug Tracker, https://github.com/pshlego/Anomaly_Explanation/issues
Author-email: Hyukkyu Kang <hyukkyukang@gmail.com>
License-File: LICENSE
Classifier: License :: OSI Approved :: MIT License
Classifier: Operating System :: OS Independent
Classifier: Programming Language :: Python :: 3
Requires-Python: >=3.6
Requires-Dist: gdown
Requires-Dist: hkkang-utils
Requires-Dist: hydra-core
Requires-Dist: omegaconf
Requires-Dist: pandas
Requires-Dist: pillow
Requires-Dist: scikit-learn
Requires-Dist: wget
